{
  "EmbedMap": {
    "description": "Auto imported from components/EmbedMap.vue"
  },
  "Gallery": {
    "description": "Auto imported from components/Gallery.vue"
  },
  "Loading": {
    "description": "Auto imported from components/Loading.vue"
  },
  "Social": {
    "description": "Auto imported from components/Social.vue"
  },
  "Tiles": {
    "description": "Auto imported from components/Tiles.vue"
  },
  "ElementsCustomCursor": {
    "description": "Auto imported from components/Elements/CustomCursor.vue"
  },
  "PageFooter": {
    "description": "Auto imported from components/Page/PageFooter.vue"
  },
  "PageHeader": {
    "description": "Auto imported from components/Page/PageHeader.vue"
  },
  "PageWrapper": {
    "description": "Auto imported from components/Page/PageWrapper.vue"
  }
}
